Metadata-Version: 1.0
Name: socketqueue
Version: 0.3.0
Summary: crossplatform Abastraction Interface to epool, kqueue, select, pool and IOCP(someday)
Home-page: http://github.com/caetanus/socketqueue
Author: Marcelo Aires Caetano
Author-email: marcelo@fiveti.com
License: BSD
Keywords: epool kqueue select iocp
Platform: UNKNOWN
